ServerStatusMonitor/Core.py
ServerStatusMonitor/__init__.py
erispulse_serverstatusmonitor-1.1.1.dist-info/licenses/LICENSE
erispulse_serverstatusmonitor-1.1.1.dist-info/METADATA
erispulse_serverstatusmonitor-1.1.1.dist-info/WHEEL
erispulse_serverstatusmonitor-1.1.1.dist-info/entry_points.txt
erispulse_serverstatusmonitor-1.1.1.dist-info/top_level.txt
erispulse_serverstatusmonitor-1.1.1.dist-info/RECORD
