Metadata-Version: 2.4
Name: ErisPulse-ServerStatusMonitor
Version: 1.1.1
Summary: ErisPulse 系统信息查询模块
Author-email: wsu2059q <wsu2059@qq.com>
License: MIT License
Project-URL: homepage, https://github.com/wsu2059q/ErisPulse-ServerStatusMonitor
Requires-Python: >=3.9
License-File: LICENSE
Requires-Dist: ErisPulse-SystemStatus
Dynamic: license-file
